{
  "pages": {
    "/": [
      "HomeA",
      "HomeB",
      "HomeC",
      "HomeD",
      "HomeE",
      "HomeF",
      "HomeG",
      "HomeH",
      "HomeI",
      "HomeL"
    ],
    "/aboutus": [
      "AboutA",
      "AboutB",
      "AboutC",
      "AboutD",
      "AboutE",
      "AboutF",
      "AboutG",
      "AboutH"
    ],
    "/team": [
      "TeamA",
      "TeamB",
      "TeamC",
      "TeamD"
    ],
    "/contact": [
      "ContactA",
      "ContactB"
    ],
    "/home-one": [
      "HomeOneA",
      "HomeOneB",
      "HomeOneC",
      "HomeOneD",
      "HomeOneE",
      "HomeOneF",
      "HomeOneG",
      "HomeOneH"
    ],
    "/home-two": [
      "HomeTwoA",
      "HomeTwoB",
      "HomeTwoC",
      "HomeTwoD",
      "HomeTwoE",
      "HomeTwoF",
      "HomeTwoG",
      "HomeTwoH",
      "HomeTwoI",
      "HomeTwoJ"
    ],
    "/pricing-one": [
      "PricingA",
      "PricingB"
    ],
    "/service-one": [
      "ServiceOneA",
      "ServiceOneB",
      "ServiceOneC",
      "ServiceOneD",
      "ServiceOneE",
      "ServiceOneF"
    ],
    "/service-two": [
      "ServiceTwoA",
      "ServiceTwoB",
      "ServiceTwoC",
      "ServiceTwoD"
    ]
  },
  "sharedComponents": [
    "Header",
    "Footer"
  ],
  "lastUpdated": "2025-11-25T08:40:22.105Z"
}